bloxflippredictor/__init__.py
bloxflippredictor/crash.py
bloxflippredictor/mines.py
bloxflippredictor/roulette.py
bloxflippredictor/towers.py
bloxflippredictor-3.1.4.dist-info/LICENSE
bloxflippredictor-3.1.4.dist-info/METADATA
bloxflippredictor-3.1.4.dist-info/WHEEL
bloxflippredictor-3.1.4.dist-info/top_level.txt
bloxflippredictor-3.1.4.dist-info/RECORD
